<annotation>
	<folder>images</folder>
	<filename>happy5.jpg</filename>
	<path>D:\Programming Code\ML\RealTimeObjectDetection\Tensorflow\workspace\images\images\happy5.jpg</path>
	<source>
		<database>Unknown</database>
	</source>
	<size>
		<width>1920</width>
		<height>1080</height>
		<depth>3</depth>
	</size>
	<segmented>0</segmented>
	<object>
		<name>happy</name>
		<pose>Unspecified</pose>
		<truncated>0</truncated>
		<difficult>0</difficult>
		<bndbox>
			<xmin>722</xmin>
			<ymin>190</ymin>
			<xmax>1250</xmax>
			<ymax>476</ymax>
		</bndbox>
	</object>
</annotation>
