<annotation>
	<folder>images</folder>
	<filename>loud6.jpg</filename>
	<path>D:\Programming Code\ML\RealTimeObjectDetection\Tensorflow\workspace\images\images\loud6.jpg</path>
	<source>
		<database>Unknown</database>
	</source>
	<size>
		<width>1920</width>
		<height>1080</height>
		<depth>3</depth>
	</size>
	<segmented>0</segmented>
	<object>
		<name>loud</name>
		<pose>Unspecified</pose>
		<truncated>0</truncated>
		<difficult>0</difficult>
		<bndbox>
			<xmin>667</xmin>
			<ymin>91</ymin>
			<xmax>1225</xmax>
			<ymax>381</ymax>
		</bndbox>
	</object>
</annotation>
